sd/__init__.py
sd/simdis.py
simple_discordpy-0.4.dist-info/LICENSE.txt
simple_discordpy-0.4.dist-info/METADATA
simple_discordpy-0.4.dist-info/WHEEL
simple_discordpy-0.4.dist-info/top_level.txt
simple_discordpy-0.4.dist-info/RECORD
