Metadata-Version: 2.1
Name: simple-discordpy
Version: 0.4
Summary: Hello world
Home-page: https://github.com/sunho/simple-discordpy
Author: Sunho Kim
Author-email: ksunhokim123@naver.com
License: UNKNOWN
Download-URL: https://github.com/sunho/simple-discordpy/archive/v2.0.0.tar.gz
Platform: UNKNOWN
Classifier: License :: OSI Approved :: MIT License
Requires-Dist: discord.py
